{
  "kind": "Template",
  "apiVersion": "v1beta3",
  "metadata": {
    "name": "rails-blog-sample",
    "creationTimestamp": null,
    "annotations": {
      "description": "A simple Ruby on Rails® blog application (no DB).",
      "iconClass": "icon-ruby",
      "tags": "instant-app,ruby,rails"
    }
  },
  "objects": [
    {
      "kind": "Service",
      "apiVersion": "v1beta3",
      "metadata": {
        "name": "frontend",
        "creationTimestamp": null
      },
      "spec": {
        "ports": [
          {
            "name": "web",
            "protocol": "TCP",
            "port": 5432,
            "targetPort": 8080,
            "nodePort": 0
          }
        ],
        "selector": {
          "name": "frontend"
        },
        "portalIP": "",
        "type": "ClusterIP",
        "sessionAffinity": "None"
      },
      "status": {
        "loadBalancer": {}
      }
    },
    {
      "kind": "ImageStream",
      "apiVersion": "v1beta3",
      "metadata": {
        "name": "origin-rails-blog",
        "creationTimestamp": null
      },
      "spec": {},
      "status": {
        "dockerImageRepository": ""
      }
    },
    {
      "kind": "ImageStream",
      "apiVersion": "v1beta3",
      "metadata": {
        "name": "ruby-20-centos7",
        "creationTimestamp": null
      },
      "spec": {
        "dockerImageRepository": "openshift/ruby-20-centos7"
      },
      "status": {
        "dockerImageRepository": ""
      }
    },
    {
      "kind": "BuildConfig",
      "apiVersion": "v1beta3",
      "metadata": {
        "name": "rails-blog",
        "creationTimestamp": null,
        "labels": {
          "name": "rails-blog"
        }
      },
      "spec": {
        "triggers": [
          {
            "type": "github",
            "github": {
              "secret": "secret101"
            }
          },
          {
            "type": "generic",
            "generic": {
              "secret": "secret101"
            }
          },
          {
            "type": "imageChange",
            "imageChange": {}
          }
        ],
        "source": {
          "type": "Git",
          "git": {
            "uri": "${GITHUB_URL}"
          }
        },
        "strategy": {
          "type": "Source",
          "sourceStrategy": {
            "from": {
              "kind": "DockerImage",
              "name": "openshift/ruby-20-centos7:latest"
            },
            "incremental": true
          }
        },
        "output": {
          "to": {
            "kind": "ImageStreamTag",
            "name": "origin-rails-blog:latest"
          }
        },
        "resources": {}
      },
      "status": {
        "lastVersion": 0
      }
    },
    {
      "kind": "DeploymentConfig",
      "apiVersion": "v1beta3",
      "metadata": {
        "name": "frontend",
        "creationTimestamp": null
      },
      "spec": {
        "strategy": {
          "type": "Rolling",
          "rollingParams": {
            "updatePeriodSeconds": 1,
            "intervalSeconds": 1,
            "timeoutSeconds": 120
          },
          "resources": {}
        },
        "triggers": [
          {
            "type": "ImageChange",
            "imageChangeParams": {
              "automatic": true,
              "containerNames": [
                "rails-blog"
              ],
              "from": {
                "name": "origin-rails-blog:latest"
              },
              "lastTriggeredImage": ""
            }
          }
        ],
        "replicas": 1,
        "selector": {
          "name": "frontend"
        },
        "template": {
          "metadata": {
            "creationTimestamp": null,
            "labels": {
              "name": "frontend"
            }
          },
          "spec": {
            "containers": [
              {
                "name": "rails-blog",
                "image": "origin-rails-blog",
                "ports": [
                  {
                    "containerPort": 8080,
                    "protocol": "TCP"
                  }
                ],
                "resources": {},
                "terminationMessagePath": "/dev/termination-log",
                "imagePullPolicy": "IfNotPresent",
                "capabilities": {},
                "securityContext": {
                  "capabilities": {},
                  "privileged": false
                }
              }
            ],
            "restartPolicy": "Always",
            "dnsPolicy": "ClusterFirst"
          }
        }
      },
      "status": {}
    }
  ],
  "parameters": [
    {
      "name": "GITHUB_URL",
      "description": "The URL with your Rails application source code.",
      "value": "git://github.com/ewolinetz/ruby-rails-example.git"
    },
    {
      "name": "SECRET_KEY_BASE",
      "description": "Your secret key for verifying the integrity of signed cookies.",
      "generate": "expression",
      "from": "[a-z0-9]{127}"
    },
    {
      "name": "FRONTEND_ROUTE",
      "description": "The exposed hostname that will route Rails frontend service.",
      "value": "rails-frontend.apps"
    }
  ],
  "labels": {
    "template": "application-template-stibuild"
  }
}

